__init__.py
kaydet.py
kaydet-0.8.6.dist-info/LICENSE
kaydet-0.8.6.dist-info/METADATA
kaydet-0.8.6.dist-info/WHEEL
kaydet-0.8.6.dist-info/entry_points.txt
kaydet-0.8.6.dist-info/top_level.txt
kaydet-0.8.6.dist-info/RECORD
