Metadata-Version: 2.1
Name: kaydet
Version: 0.8.6
Summary: Simple and terminal-based personal diary app designed to help you preserve your daily thoughts, experiences, and memories.
Home-page: https://github.com/miratcan/logme
Author: Mirat Can Bayrak
License: MIT
Keywords: diary tui
Classifier: License :: OSI Approved :: MIT License
Classifier: Programming Language :: Python :: 3.8
Classifier: Programming Language :: Python :: 3.9
Classifier: Programming Language :: Python :: 3.10
Classifier: Programming Language :: Python :: 3.11
Classifier: Development Status :: 4 - Beta
Classifier: Environment :: Console
Classifier: Intended Audience :: Information Technology
Classifier: Natural Language :: English
Classifier: Topic :: Utilities
Classifier: Topic :: Utilities
Classifier: Topic :: Utilities
Classifier: Topic :: Utilities
Requires-Python: >=3.4
License-File: LICENSE
Requires-Dist: universal-startfile (==0.2)
